universal_uploader_widget/__init__.py
universal_uploader_widget/admin.py
universal_uploader_widget/widgets.py
universal_uploader_widget/__pycache__/__init__.cpython-38.pyc
universal_uploader_widget/__pycache__/admin.cpython-38.pyc
universal_uploader_widget/__pycache__/widgets.cpython-38.pyc
universal_uploader_widget/locale/pt_BR/LC_MESSAGES/django.mo
universal_uploader_widget/locale/pt_BR/LC_MESSAGES/django.po
universal_uploader_widget/static/admin/css/.gitignore
universal_uploader_widget/static/admin/css/universal-uploader-inline.css
universal_uploader_widget/static/admin/css/universal-uploader-inline.min.css
universal_uploader_widget/static/admin/css/universal-uploader-widget.css
universal_uploader_widget/static/admin/css/universal-uploader-widget.min.css
universal_uploader_widget/static/admin/js/.gitignore
universal_uploader_widget/static/admin/js/universal-uploader-inline.js
universal_uploader_widget/static/admin/js/universal-uploader-inline.min.js
universal_uploader_widget/static/admin/js/universal-uploader-inline.min.js.LICENSE.txt
universal_uploader_widget/static/admin/js/universal-uploader-widget.js
universal_uploader_widget/static/admin/js/universal-uploader-widget.min.js
universal_uploader_widget/static/admin/js/universal-uploader-widget.min.js.LICENSE.txt
universal_uploader_widget/static/admin/vendor/pdf.worker.min.js
universal_uploader_widget/templates/admin/edit_inline/universal_uploader.html
universal_uploader_widget/templates/admin/widgets/universal_uploader_widget.html
django_universal_uploader_widget-0.2.4.dist-info/LICENSE
django_universal_uploader_widget-0.2.4.dist-info/METADATA
django_universal_uploader_widget-0.2.4.dist-info/WHEEL
django_universal_uploader_widget-0.2.4.dist-info/top_level.txt
django_universal_uploader_widget-0.2.4.dist-info/RECORD
