Metadata-Version: 2.1
Name: django-universal-uploader-widget
Version: 0.2.4
Summary: Simple Universal Uploader Widget for Django-Admin
Home-page: https://github.com/sandro-salles/django-universal-uploader-widget
Author: Sandro Salles
Author-email: sandro@snippet.com.br
License: MIT
Keywords: django,admin,widget,universal,uploader
Classifier: Development Status :: 5 - Production/Stable
Classifier: Environment :: Web Environment
Classifier: Framework :: Django
Classifier: Intended Audience :: Developers
Classifier: License :: OSI Approved :: MIT License
Classifier: Operating System :: OS Independent
Classifier: Programming Language :: Python
Classifier: Programming Language :: Python :: 3
Classifier: Programming Language :: Python :: 3.4
Classifier: Programming Language :: Python :: 3.5
Classifier: Programming Language :: Python :: 3.6
License-File: LICENSE
